LICENSE.txt
README.md
setup.cfg
setup.py
pingdiscover.egg-info/PKG-INFO
pingdiscover.egg-info/SOURCES.txt
pingdiscover.egg-info/dependency_links.txt
pingdiscover.egg-info/entry_points.txt
pingdiscover.egg-info/requires.txt
pingdiscover.egg-info/top_level.txt
src/__init__.py
src/pingdiscover.py