Metadata-Version: 2.1
Name: pingdiscover
Version: 1.1.1
Summary: A simple commandline app for ip lookup with concurrent processes
Home-page: UNKNOWN
Author: Ilkin Mammadov
Author-email: ilkma1998@gmail.com
License: MIT
Platform: UNKNOWN
Classifier: License :: OSI Approved :: MIT License
Classifier: Programming Language :: Python :: 3
Classifier: Programming Language :: Python :: 3.7
Requires-Python: >=3.7
License-File: LICENSE.txt
